tcplite/__init__.py
tcplite/client.py
tcplite/packet.py
tcplite/server.py
tcplite-0.0.3.dist-info/LICENSE
tcplite-0.0.3.dist-info/METADATA
tcplite-0.0.3.dist-info/WHEEL
tcplite-0.0.3.dist-info/top_level.txt
tcplite-0.0.3.dist-info/RECORD
